pytest_idem/plugin.py
pytest_idem/run.py
pytest_idem/runner.py
pytest_idem-4.0.1.dist-info/LICENSE
pytest_idem-4.0.1.dist-info/METADATA
pytest_idem-4.0.1.dist-info/WHEEL
pytest_idem-4.0.1.dist-info/entry_points.txt
pytest_idem-4.0.1.dist-info/top_level.txt
pytest_idem-4.0.1.dist-info/RECORD
