Metadata-Version: 2.1
Name: pytest-idem
Version: 4.0.1
Summary: A pytest plugin to help with testing idem projects
Home-page: https://gitlab.com/saltstack/idem/pytest-idem
Author: Tyler Johnson
Author-email: tjohnson@saltstack.com
Classifier: Framework :: Pytest
Classifier: Intended Audience :: Developers
Classifier: Topic :: Software Development :: Testing
Classifier: Operating System :: OS Independent
Classifier: Programming Language :: Python
Classifier: Programming Language :: Python :: 3.8
Classifier: Programming Language :: Python :: 3.9
Classifier: Programming Language :: Python :: 3.10
Classifier: Programming Language :: Python :: 3.11
Classifier: Development Status :: 5 - Production/Stable
Requires-Python: >=3.8
License-File: LICENSE
Requires-Dist: pytest-pop >=9.0.0
Requires-Dist: idem >=18.5.0
Requires-Dist: pyyaml >=6.0.1
